cca_zoo/__init__.py
cca_zoo/_base.py
cca_zoo/_utils/__init__.py
cca_zoo/_utils/_checks.py
cca_zoo/_utils/_cross_correlation.py
cca_zoo/_utils/_splitter.py
cca_zoo/datasets/__init__.py
cca_zoo/datasets/simulated.py
cca_zoo/datasets/toy.py
cca_zoo/deep/__init__.py
cca_zoo/deep/_base.py
cca_zoo/deep/_discriminative/__init__.py
cca_zoo/deep/_discriminative/_barlow_twins.py
cca_zoo/deep/_discriminative/_dcca.py
cca_zoo/deep/_discriminative/_dcca_ey.py
cca_zoo/deep/_discriminative/_dcca_gha.py
cca_zoo/deep/_discriminative/_dcca_noi.py
cca_zoo/deep/_discriminative/_dcca_sdl.py
cca_zoo/deep/_discriminative/_dcca_svd.py
cca_zoo/deep/_discriminative/_dgcca.py
cca_zoo/deep/_discriminative/_dmcca.py
cca_zoo/deep/_discriminative/_dtcca.py
cca_zoo/deep/_discriminative/_vicreg.py
cca_zoo/deep/_generative/__init__.py
cca_zoo/deep/_generative/_dccae.py
cca_zoo/deep/_generative/_dvcca.py
cca_zoo/deep/_utils.py
cca_zoo/deep/architectures.py
cca_zoo/deep/data.py
cca_zoo/linear/__init__.py
cca_zoo/linear/_dummy.py
cca_zoo/linear/_gcca.py
cca_zoo/linear/_gradient/__init__.py
cca_zoo/linear/_gradient/_base.py
cca_zoo/linear/_gradient/_ey.py
cca_zoo/linear/_gradient/_gha.py
cca_zoo/linear/_gradient/_objectives.py
cca_zoo/linear/_gradient/_stochasticpls.py
cca_zoo/linear/_gradient/_svd.py
cca_zoo/linear/_gradient/_tracenorm.py
cca_zoo/linear/_grcca.py
cca_zoo/linear/_iterative/__init__.py
cca_zoo/linear/_iterative/_altmaxvar.py
cca_zoo/linear/_iterative/_base.py
cca_zoo/linear/_iterative/_deflation.py
cca_zoo/linear/_iterative/_elastic.py
cca_zoo/linear/_iterative/_incrementalpls.py
cca_zoo/linear/_iterative/_pls_als.py
cca_zoo/linear/_iterative/_scca_admm.py
cca_zoo/linear/_iterative/_scca_parkhomenko.py
cca_zoo/linear/_iterative/_scca_span.py
cca_zoo/linear/_iterative/_spls.py
cca_zoo/linear/_iterative/_swcca.py
cca_zoo/linear/_mcca.py
cca_zoo/linear/_partialcca.py
cca_zoo/linear/_pcacca.py
cca_zoo/linear/_pls.py
cca_zoo/linear/_plsregression.py
cca_zoo/linear/_prcca.py
cca_zoo-2.6.0.dist-info/LICENSE
cca_zoo-2.6.0.dist-info/METADATA
cca_zoo-2.6.0.dist-info/WHEEL
cca_zoo-2.6.0.dist-info/RECORD
