Metadata-Version: 2.1
Name: cca-zoo
Version: 2.6.0
Summary: Canonical Correlation Analysis Zoo: A collection of Regularized, Deep Learning based, Kernel, and Probabilistic methods in a scikit-learn style framework
Home-page: https://github.com/jameschapman19/cca_zoo
License: MIT
Keywords: cca
Author: jameschapman
Author-email: james.chapman.19@ucl.ac.uk
Requires-Python: >=3.8,<4.0.0
Classifier: License :: OSI Approved :: MIT License
Classifier: Programming Language :: Python :: 3
Classifier: Programming Language :: Python :: 3.8
Classifier: Programming Language :: Python :: 3.9
Classifier: Programming Language :: Python :: 3.10
Classifier: Programming Language :: Python :: 3.11
Classifier: Programming Language :: Python :: 3.12
Provides-Extra: deep
Provides-Extra: probabilistic
Provides-Extra: visualisation
Requires-Dist: arviz ; extra == "probabilistic"
Requires-Dist: funsor ; extra == "probabilistic"
Requires-Dist: jax ; extra == "probabilistic"
Requires-Dist: lightning ; extra == "deep"
Requires-Dist: numpyro ; extra == "probabilistic"
Requires-Dist: scikit-learn (>=1.2.2,<2.0.0)
Requires-Dist: tensorly
Requires-Dist: torch (>=2.0.1,<3.0.0) ; (sys_platform == "darwin") and (extra == "deep")
Requires-Dist: torch (>=2.0.1,<3.0.0) ; (sys_platform == "linux") and (extra == "deep")
Requires-Dist: torch (>=2.0.1,<3.0.0) ; (sys_platform == "win32") and (extra == "deep")
Requires-Dist: tqdm
